pipe_operator/__init__.py
pipe_operator/elixir_flow/__init__.py
pipe_operator/elixir_flow/pipe.py
pipe_operator/elixir_flow/transformers.py
pipe_operator/elixir_flow/utils.py
pipe_operator/elixir_flow/tests/__init__.py
pipe_operator/elixir_flow/tests/test_pipe.py
pipe_operator/elixir_flow/tests/test_transformers.py
pipe_operator/elixir_flow/tests/test_utils.py
pipe_operator/python_flow/__init__.py
pipe_operator/python_flow/classes.py
pipe_operator/python_flow/tests.py
pipe_operator/python_flow/types.py
pipe_operator/python_flow/utils.py
pipe_operator/shared/__init__.py
pipe_operator/shared/exceptions.py
pipe_operator/shared/utils.py
pipe_operator/shared/tests/__init__.py
pipe_operator/shared/tests/test_utils.py
pipe_operator-2.1.0.dist-info/licenses/LICENSE
pipe_operator-2.1.0.dist-info/METADATA
pipe_operator-2.1.0.dist-info/WHEEL
pipe_operator-2.1.0.dist-info/top_level.txt
pipe_operator-2.1.0.dist-info/RECORD
