Metadata-Version: 2.4
Name: pipe_operator
Version: 2.1.0
Summary: Elixir's pipe operator in Python
Author-email: Jordan Kowal <kowaljordan@gmail.com>
Maintainer-email: Jordan Kowal <kowaljordan@gmail.com>
License: Copyright 2018 Robin Hilliard
Project-URL: Changelog, https://github.com/Jordan-Kowal/pipe-operator/blob/main/CHANGELOG.md
Project-URL: Issues, https://github.com/Jordan-Kowal/pipe-operator/issues
Project-URL: Release notes, https://github.com/Jordan-Kowal/pipe-operator/releases
Project-URL: Source, https://github.com/Jordan-Kowal/pipe-operator
Keywords: pipe,operator,elixir
Classifier: Development Status :: 5 - Production/Stable
Classifier: Intended Audience :: Developers
Classifier: License :: OSI Approved :: MIT License
Classifier: Operating System :: Microsoft :: Windows
Classifier: Operating System :: POSIX
Classifier: Operating System :: Unix
Classifier: Operating System :: MacOS
Classifier: Programming Language :: Python
Classifier: Programming Language :: Python :: 3
Classifier: Programming Language :: Python :: 3.9
Classifier: Programming Language :: Python :: 3.10
Classifier: Programming Language :: Python :: 3.11
Classifier: Programming Language :: Python :: 3.12
Classifier: Programming Language :: Python :: 3.13
Classifier: Programming Language :: Python :: 3.14
Classifier: Programming Language :: Python :: Implementation :: CPython
Classifier: Topic :: Software Development
Requires-Python: >=3.9
License-File: LICENSE
Requires-Dist: typing-extensions>=4.12.2
Dynamic: license-file
